LICENSE.txt
MANIFEST.in
Makefile
README.rst
VERSION.txt
pylintrc
pyproject.toml
setup.cfg
tox.ini
data/time00/Image_00019.dcm
data/time00/Image_00020.dcm
data/time00/Image_00021.dcm
src/imagedata_transport_s3/__init__.py
src/imagedata_transport_s3/s3transport.py
src/imagedata_transport_s3.egg-info/PKG-INFO
src/imagedata_transport_s3.egg-info/SOURCES.txt
src/imagedata_transport_s3.egg-info/dependency_links.txt
src/imagedata_transport_s3.egg-info/entry_points.txt
src/imagedata_transport_s3.egg-info/requires.txt
src/imagedata_transport_s3.egg-info/top_level.txt
tests/__init__.py
tests/test_transport_s3.py