Metadata-Version: 2.1
Name: imagedata_transport_s3
Version: 1.0.3
Summary: Imagedata transport plugin for S3/Minio storage
Home-page: https://github.com/erling6232/imagedata_transport_s3
Author: Erling Andersen
Author-email: Erling.Andersen@Helse-Bergen.NO
License: MIT
Project-URL: Documentation, https://imagedata.readthedocs.io
Project-URL: Source Code, https://github.com/erling6232/imagedata_transport_s3
Keywords: python,medical,imaging,s3,minio
Classifier: Programming Language :: Python :: 3
Classifier: Development Status :: 4 - Beta
Classifier: Environment :: Other Environment
Classifier: Intended Audience :: Developers
Classifier: Intended Audience :: Healthcare Industry
Classifier: Intended Audience :: Science/Research
Classifier: License :: OSI Approved :: MIT License
Classifier: Operating System :: OS Independent
Classifier: Topic :: Software Development :: Libraries :: Python Modules
Classifier: Topic :: Scientific/Engineering :: Medical Science Apps.
Requires-Python: <3.13,>=3.8
License-File: LICENSE.txt
Requires-Dist: imagedata>=3.4.3
Requires-Dist: minio
